<map name="冰之谷" category="5" id="401" weather="0" switch="1">
	<!-- <resource>10011</resource> -->
	<initialPoint>620,120</initialPoint>
	<music category="5">
		<bgm>BGM_025</bgm>
	</music>
	<entities>

		<npc id="40101" resId="Pets/pet/122.png" name="Lv61 冻气龟" size="45,58" pos="350,230" namePos="0,0">
			<battle>
				<branch id="default">
					<settings count="6" capture="true"/>
					<enemy>
						<pet id="122" level="61">
							<loopSkill>10050</loopSkill>
						</pet>
					</enemy>
				</branch>
			</battle>
			<eventHandler>
				<button type="click">
					<action>battle</action>
					<param>default</param>
				</button>
			</eventHandler>
		</npc>
		<npc id="40102" resId="Pets/pet/122.png" name="Lv60 冻气龟" size="45,58" pos="520,120" namePos="0,0">
			<battle>
				<branch id="default">
					<settings count="6" capture="true"/>
					<enemy>
						<pet id="122" level="60">
							<loopSkill>10050</loopSkill>
						</pet>
					</enemy>
				</branch>
			</battle>
			<eventHandler>
				<button type="click">
					<action>battle</action>
					<param>default</param>
				</button>
			</eventHandler>
		</npc>
			<teleport id="1" name="冰脊山脉" pos="160,300" targetMapId="402"/>
			<teleport id="2" name="冰之监狱" pos="570,240" targetMapId="407"/>
			<teleport id="3" name="冰沁宫殿" pos="830,160" targetMapId="405"/>
			<teleport id="4" name="冰晶矿场" pos="320,60" targetMapId="404"/>
			<teleport id="5" name="实验禁地" pos="350,310" targetMapId="500"/>
			<teleport id="6" name="冰封之轴" pos="490,50" targetMapId="412"/>
	</entities>


</map>

